particleannotation/__init__.py
particleannotation/_version.py
particleannotation/napari.yaml
particleannotation/_qt/__init__.py
particleannotation/_qt/_cloud_window_viewer.py
particleannotation/_qt/_local_window_viewer.py
particleannotation/_qt/_predict.py
particleannotation/_qt/cloud_tm_score_3d_viewer_3.py
particleannotation/_qt/cloud_tm_score_3d_viewer_7.py
particleannotation/_qt/cloud_tm_score_3d_viewer_ecoli.py
particleannotation/_qt/local_tm_score_3d_predict_viewer.py
particleannotation/_qt/local_tm_score_3d_viewer.py
particleannotation/_qt/local_tm_score_3d_viewer_ecoli.py
particleannotation/_qt/upload.py
particleannotation/_qt/upload_3d.py
particleannotation/_qt/viewer_utils.py
particleannotation/cloud/__init__.py
particleannotation/cloud/_aws_api.py
particleannotation/cloud/aws_api_3d.py
particleannotation/cloud/datatypes.py
particleannotation/cloud/utils.py
particleannotation/utils/__init__.py
particleannotation/utils/_reader.py
particleannotation/utils/export_data.py
particleannotation/utils/load_data.py
particleannotation/utils/pc_sampling.py
particleannotation/utils/scale.py
particleannotation/utils/model/__init__.py
particleannotation/utils/model/active_learning_model.py
particleannotation/utils/model/utils.py
particleannotation/utils/viewer/__init__.py
particleannotation/utils/viewer/viewer_functionality.py
tests/__init__.py
tests/test_api.py
tests/test_api_3d.py
tests/test_general.py
tests/test_viewer_utils.py
tests/api/data/models/topaz_al_model_000.pth
particleannotation-0.3.9.dist-info/LICENSE
particleannotation-0.3.9.dist-info/METADATA
particleannotation-0.3.9.dist-info/WHEEL
particleannotation-0.3.9.dist-info/entry_points.txt
particleannotation-0.3.9.dist-info/top_level.txt
particleannotation-0.3.9.dist-info/RECORD
